placer
pythunder.cpython-38-darwin.so
pythunder-0.4.3.data/scripts/placer
pythunder-0.4.3.dist-info/LICENSE.txt
pythunder-0.4.3.dist-info/METADATA
pythunder-0.4.3.dist-info/WHEEL
pythunder-0.4.3.dist-info/top_level.txt
pythunder-0.4.3.dist-info/RECORD
