Metadata-Version: 2.1
Name: pythunder
Version: 0.4.3
Summary: Fast CGRA Placement
Home-page: https://github.com/Kuree/cgra_pnr/tree/master/thunder
Author: Keyi Zhang
Author-email: keyi@stanford.edu
License: UNKNOWN
Platform: UNKNOWN
